{"spec":{"projectName":"TEST8","appsData":[{"metadata":{"name":"firewall","description":"desc of firewall","UserData1":"data 1","UserData2":"data2","chartContent":"","status":""},"placementCriterion":"allOf","placementType":"labels","clusters":[{"clusterProvider":"provider-1","selectedClusters":[{"name":"clu-48"}]}]},{"metadata":{"name":"packetgen","description":"desc of packetgen","UserData1":"data 1","UserData2":"data2","chartContent":"","status":""},"placementCriterion":"allOf","placementType":"labels","clusters":[{"clusterProvider":"provider-1","selectedClusters":[{"name":"clu-48"}]}]},{"metadata":{"name":"sink","description":"desc of sink","UserData1":"data 1","UserData2":"data2","chartContent":"","status":""},"placementCriterion":"allOf","placementType":"labels","clusters":[{"clusterProvider":"provider-1","selectedClusters":[{"name":"clu-48"}]}]}]},"name":"vfw1_1","description":"","compositeProfile":"vFW1_profile","version":"v1","compositeApp":"vFW1","compositeAppVersion":"v1","logicalCloud":"lc2"}
